setup.py
client/__init__.py
client/client_script.py
client/setup_client.py
client/client/__init__.py
client/client/client_classfile.py
client/client/db/__init__.py
client/client/db/client_db.py
client/client/gui/__init__.py
client/client/gui/add_contact.py
client/client/gui/del_contact.py
client/client/gui/main_window.py
client/client/gui/main_window_ui.py
client/client/gui/welcome_window.py
client/common/__init__.py
client/common/decorators.py
client/common/descriptors.py
client/common/errors.py
client/common/metaclasses.py
client/common/parent_classfile.py
client/common/vars.py
client/project_logging/__init__.py
client/project_logging/configs/__init__.py
client/project_logging/configs/client_log_config.py
client/project_logging/configs/server_log_config.py
client/project_logging/log/__init__.py
mess_client_test_Ensueno.egg-info/PKG-INFO
mess_client_test_Ensueno.egg-info/SOURCES.txt
mess_client_test_Ensueno.egg-info/dependency_links.txt
mess_client_test_Ensueno.egg-info/requires.txt
mess_client_test_Ensueno.egg-info/top_level.txt